ibge/__init__.py
ibge/localidades.py
ibge-0.0.5.dist-info/LICENSE
ibge-0.0.5.dist-info/METADATA
ibge-0.0.5.dist-info/WHEEL
ibge-0.0.5.dist-info/top_level.txt
ibge-0.0.5.dist-info/RECORD
