Metadata-Version: 2.1
Name: ibge
Version: 0.0.5
Summary: Collection of APIs for the IBGE Data Services in Brazil
Home-page: https://github.com/leogregianin/ibge/
Author: Leonardo Gregianin, Gustavo Efeiche
Author-email: leogregianin@gmail.com
License: MIT
Project-URL: Documentation, https://github.com/leogregianin/ibge/blob/master/README.md
Platform: UNKNOWN
Classifier: Development Status :: 4 - Beta
Classifier: License :: OSI Approved :: MIT License
Classifier: Programming Language :: Python :: 3 :: Only
Classifier: Programming Language :: Python :: 3.5
Classifier: Programming Language :: Python :: 3.6
Classifier: Programming Language :: Python :: 3.7
Classifier: Programming Language :: Python :: 3.8
Classifier: Topic :: Software Development :: Libraries
Classifier: Topic :: Software Development :: Libraries :: Python Modules
Classifier: Intended Audience :: Developers
Classifier: Operating System :: OS Independent
Classifier: Natural Language :: Portuguese (Brazilian)
Requires-Python: >=3.5
